srctypes/__init__.py
srctypes/py.typed
srctypes-0.1.0.dist-info/METADATA
srctypes-0.1.0.dist-info/WHEEL
srctypes-0.1.0.dist-info/licenses/LICENSE
srctypes-0.1.0.dist-info/RECORD
